element_maker/__init__.py
element_maker/utils.py
lxml_element_maker-1.0.1.dist-info/DESCRIPTION.rst
lxml_element_maker-1.0.1.dist-info/METADATA
lxml_element_maker-1.0.1.dist-info/RECORD
lxml_element_maker-1.0.1.dist-info/WHEEL
lxml_element_maker-1.0.1.dist-info/metadata.json
lxml_element_maker-1.0.1.dist-info/top_level.txt
tests/__init__.py
tests/test_utils.py
