Metadata-Version: 2.0
Name: lxml-element-maker
Version: 1.0.1
Summary: Transforms a python structure to an xml element with lxml
Home-page: https://github.com/unistra/lxml-element-maker
Author: di-dip-unistra
Author-email: di-dip@unistra.fr
License: PSF
Download-URL: http://pypi.python.org/pypi/lxml-element-maker
Keywords: lxml,python,maker,xml,element
Platform: UNKNOWN
Classifier: Development Status :: 4 - Beta
Classifier: Intended Audience :: Developers
Classifier: License :: OSI Approved :: Python Software Foundation License
Classifier: Operating System :: OS Independent
Classifier: Programming Language :: Python :: 3.4
Requires-Dist: lxml (==3.4.4)
